odoo/addons/sale_partner_incoterm/README.rst
odoo/addons/sale_partner_incoterm/__init__.py
odoo/addons/sale_partner_incoterm/__manifest__.py
odoo/addons/sale_partner_incoterm/i18n/ca.po
odoo/addons/sale_partner_incoterm/i18n/de.po
odoo/addons/sale_partner_incoterm/i18n/es.po
odoo/addons/sale_partner_incoterm/i18n/fi.po
odoo/addons/sale_partner_incoterm/i18n/fr.po
odoo/addons/sale_partner_incoterm/i18n/it.po
odoo/addons/sale_partner_incoterm/i18n/nl.po
odoo/addons/sale_partner_incoterm/i18n/sale_partner_incoterm.pot
odoo/addons/sale_partner_incoterm/i18n/sl.po
odoo/addons/sale_partner_incoterm/i18n/tr.po
odoo/addons/sale_partner_incoterm/i18n/zh_CN.po
odoo/addons/sale_partner_incoterm/models/__init__.py
odoo/addons/sale_partner_incoterm/models/res_partner.py
odoo/addons/sale_partner_incoterm/models/sale_order.py
odoo/addons/sale_partner_incoterm/readme/CONTRIBUTORS.rst
odoo/addons/sale_partner_incoterm/readme/DESCRIPTION.rst
odoo/addons/sale_partner_incoterm/static/description/icon.png
odoo/addons/sale_partner_incoterm/static/description/index.html
odoo/addons/sale_partner_incoterm/tests/__init__.py
odoo/addons/sale_partner_incoterm/tests/test_sale_partner_incoterm.py
odoo/addons/sale_partner_incoterm/views/res_partner.xml
odoo/addons/sale_partner_incoterm/views/sale_order.xml
odoo14_addon_sale_partner_incoterm-14.0.1.2.0.dist-info/METADATA
odoo14_addon_sale_partner_incoterm-14.0.1.2.0.dist-info/WHEEL
odoo14_addon_sale_partner_incoterm-14.0.1.2.0.dist-info/top_level.txt
odoo14_addon_sale_partner_incoterm-14.0.1.2.0.dist-info/RECORD
